maxdmg_back/__init__.py
maxdmg_back/app/API.py
maxdmg_back/app/Assembly.py
maxdmg_back/app/Errors.py
maxdmg_back/app/Exceptions.py
maxdmg_back/app/Form.py
maxdmg_back/app/FormElems.py
maxdmg_back/app/StateHistory.py
maxdmg_back/app/StateMachine.py
maxdmg_back/app/Types.py
maxdmg_back/app/APIs/Messages.py
maxdmg_back/app/APIs/MonoAPI.py
maxdmg_back/app/APIs/__init__.py
maxdmg_back/app/Factories/APIFactory.py
maxdmg_back/app/Factories/ActiveUsersFactory.py
maxdmg_back/app/Factories/FormElemFactory.py
maxdmg_back/app/Factories/FormFactory.py
maxdmg_back/app/Factories/StorageFactory.py
maxdmg_back/app/Factories/__init__.py
maxdmg_back/app/Interface/Form.py
maxdmg_back/app/Interface/FormElem.py
maxdmg_back/app/Interface/__init__.py
maxdmg_back/app/Storage/ActiveUsers.py
maxdmg_back/app/Storage/Context.py
maxdmg_back/app/Storage/Models.py
maxdmg_back/app/Storage/Storage.py
maxdmg_back/app/Storage/StorageInterface.py
maxdmg_back/app/Storage/__init__.py
maxdmg_back-0.0.5.dist-info/METADATA
maxdmg_back-0.0.5.dist-info/WHEEL
maxdmg_back-0.0.5.dist-info/top_level.txt
maxdmg_back-0.0.5.dist-info/RECORD
