Metadata-Version: 2.1
Name: maxdmg-back
Version: 0.0.5
Summary: This is a backend for maxdmg project.
Author: tonotonokon
Classifier: Programming Language :: Python :: 3
Classifier: License :: OSI Approved :: MIT License
Classifier: Operating System :: OS Independent
Requires-Python: >=3.10
